pymc3_ext/__init__.py
pymc3_ext/blocking.py
pymc3_ext/data.py
pymc3_ext/estimates.py
pymc3_ext/exceptions.py
pymc3_ext/math.py
pymc3_ext/memoize.py
pymc3_ext/model.py
pymc3_ext/model_graph.py
pymc3_ext/parallel_sampling.py
pymc3_ext/sampling.py
pymc3_ext/theanof.py
pymc3_ext/util.py
pymc3_ext/vartypes.py
pymc3_ext/backends/__init__.py
pymc3_ext/backends/base.py
pymc3_ext/backends/hdf5.py
pymc3_ext/backends/ndarray.py
pymc3_ext/backends/report.py
pymc3_ext/backends/sqlite.py
pymc3_ext/backends/text.py
pymc3_ext/backends/tracetab.py
pymc3_ext/distributions/__init__.py
pymc3_ext/distributions/bound.py
pymc3_ext/distributions/continuous.py
pymc3_ext/distributions/discrete.py
pymc3_ext/distributions/dist_math.py
pymc3_ext/distributions/distribution.py
pymc3_ext/distributions/mixture.py
pymc3_ext/distributions/multivariate.py
pymc3_ext/distributions/shape_utils.py
pymc3_ext/distributions/simulator.py
pymc3_ext/distributions/special.py
pymc3_ext/distributions/timeseries.py
pymc3_ext/distributions/transforms.py
pymc3_ext/examples/GHME_2013.py
pymc3_ext/examples/LKJ_correlation.py
pymc3_ext/examples/__init__.py
pymc3_ext/examples/arbitrary_stochastic.py
pymc3_ext/examples/arma_example.py
pymc3_ext/examples/baseball.py
pymc3_ext/examples/custom_dists.py
pymc3_ext/examples/disaster_model.py
pymc3_ext/examples/disaster_model_theano_op.py
pymc3_ext/examples/factor_potential.py
pymc3_ext/examples/garch_example.py
pymc3_ext/examples/gelman_bioassay.py
pymc3_ext/examples/gelman_schools.py
pymc3_ext/examples/lasso_missing.py
pymc3_ext/examples/lightspeed_example.py
pymc3_ext/examples/rankdata_ordered.py
pymc3_ext/examples/samplers_mvnormal.py
pymc3_ext/examples/simpletest.py
pymc3_ext/examples/small_probability_estimation.py
pymc3_ext/glm/__init__.py
pymc3_ext/glm/families.py
pymc3_ext/glm/linear.py
pymc3_ext/glm/utils.py
pymc3_ext/gp/__init__.py
pymc3_ext/gp/cov.py
pymc3_ext/gp/gp.py
pymc3_ext/gp/mean.py
pymc3_ext/gp/util.py
pymc3_ext/ode/__init__.py
pymc3_ext/ode/ode.py
pymc3_ext_wlad-0.2.1.dist-info/LICENSE
pymc3_ext_wlad-0.2.1.dist-info/METADATA
pymc3_ext_wlad-0.2.1.dist-info/WHEEL
pymc3_ext_wlad-0.2.1.dist-info/top_level.txt
pymc3_ext_wlad-0.2.1.dist-info/RECORD
