Metadata-Version: 2.1
Name: pymc3-ext-wlad
Version: 0.2.1
Summary: Probabilistic Programming in Python: Bayesian Modeling and Probabilistic Machine Learning with Theano
Home-page: http://github.com/wlad111/pymc3
Maintainer: PyMC Developers and wlad111
Maintainer-email: pymc.devs@gmail.com
License: Apache License, Version 2.0
Platform: UNKNOWN
Classifier: Development Status :: 5 - Production/Stable
Classifier: Programming Language :: Python
Classifier: Programming Language :: Python :: 3
Classifier: Programming Language :: Python :: 3.6
Classifier: Programming Language :: Python :: 3.7
Classifier: License :: OSI Approved :: Apache Software License
Classifier: Intended Audience :: Science/Research
Classifier: Topic :: Scientific/Engineering
Classifier: Topic :: Scientific/Engineering :: Mathematics
Classifier: Operating System :: OS Independent
Requires-Python: >=3.6
Requires-Dist: arviz (>=0.4.1)
Requires-Dist: theano (>=1.0.4)
Requires-Dist: numpy (>=1.13.0)
Requires-Dist: scipy (>=0.18.1)
Requires-Dist: pandas (>=0.18.0)
Requires-Dist: patsy (>=0.4.0)
Requires-Dist: fastprogress (>=0.2.0)
Requires-Dist: h5py (>=2.7.0)
Requires-Dist: nose (>=1.3.7)
